{
  "profile": {
    "bio": "Builder • Auto Cuan",
    "avatar": "/assets/avatar.jpg",
    "badge": {
      "text": "Open Order",
      "icon": "zap"
    }
  },

  "links": [
    {
      "id": "1",
      "title": "🔥 Order via WhatsApp",
      "url": "https://wa.me/628xxxx",
      "featured": true
    },
    {
      "id": "2",
      "title": "Portfolio",
      "url": "#"
    },
    {
      "id": "3",
      "title": "Affiliate Tools",
      "variants": [
        "https://a.com",
        "https://b.com"
      ]
    }
  ],

  "products": [
    {
      "title": "Template Link Bio",
      "price": "Rp99.000",
      "image": "/assets/avatar.jpg",
      "description": "Template siap jual",
      "demo": "#",
      "buy": "https://wa.me/628xxxx"
    }
  ],

  "gallery": [
    "/assets/avatar.jpg",
    "/assets/avatar.jpg",
    "/assets/avatar.jpg"
  ]
}
